{"openapi":"3.0.2","info":{"title":"API SIGAEST","description":"Sistema Académico y Administrativo","version":"1.0.0"},"paths":{"/api/administrativos/":{"get":{"tags":["administrativos"],"summary":"Listar todos los Docentes","operationId":"get_docentes_api_administrativos__get","responses":{"200":{"description":"La solicitud se procesó correctamente.","content":{"application/json":{"schema":{"title":"Response Get Docentes Api Administrativos  Get","type":"array","items":{"$ref":"#/components/schemas/app__routers__administrativos__DocenteResponse"}}}}},"401":{"description":"No autenticado."},"503":{"description":"Error del servidor."}},"security":[{"OAuth2PasswordBearer":[]}]}},"/api/administrativos/dni/{dni}":{"get":{"tags":["administrativos"],"summary":"Obtener un Docente por DNI","operationId":"get_docente_by_dni_api_administrativos_dni__dni__get","parameters":[{"required":true,"schema":{"title":"Dni","type":"string"},"name":"dni","in":"path"}],"responses":{"200":{"description":"La solicitud se procesó correctamente.","content":{"application/json":{"schema":{"$ref":"#/components/schemas/app__routers__administrativos__DocenteResponse"}}}},"401":{"description":"No autenticado."},"404":{"description":"Docente no encontrado."},"503":{"description":"Error del servidor."},"422":{"description":"Validation Error","content":{"application/json":{"schema":{"$ref":"#/components/schemas/HTTPValidationError"}}}}},"security":[{"OAuth2PasswordBearer":[]}]}},"/api/administrativos/{docente_id}":{"get":{"tags":["administrativos"],"summary":"Obtener un Docente por ID","operationId":"get_docente_by_id_api_administrativos__docente_id__get","parameters":[{"required":true,"schema":{"title":"Docente Id","type":"integer"},"name":"docente_id","in":"path"}],"responses":{"200":{"description":"La solicitud se procesó correctamente.","content":{"application/json":{"schema":{"$ref":"#/components/schemas/app__routers__administrativos__DocenteResponse"}}}},"401":{"description":"No autenticado."},"404":{"description":"Docente no encontrado."},"503":{"description":"Error del servidor."},"422":{"description":"Validation Error","content":{"application/json":{"schema":{"$ref":"#/components/schemas/HTTPValidationError"}}}}},"security":[{"OAuth2PasswordBearer":[]}]}},"/api/administrativos/cargo/{cargo_id}":{"get":{"tags":["administrativos"],"summary":"Obtener una lista de Docentes por ID de Cargo","operationId":"get_docentes_by_cargo_id_api_administrativos_cargo__cargo_id__get","parameters":[{"required":true,"schema":{"title":"Cargo Id","type":"integer"},"name":"cargo_id","in":"path"}],"responses":{"200":{"description":"La solicitud se procesó correctamente.","content":{"application/json":{"schema":{"title":"Response Get Docentes By Cargo Id Api Administrativos Cargo  Cargo Id  Get","type":"array","items":{"$ref":"#/components/schemas/app__routers__administrativos__DocenteResponse"}}}}},"401":{"description":"No autenticado."},"404":{"description":"No se encontraron docentes con el cargo especificado."},"503":{"description":"Error del servidor."},"422":{"description":"Validation Error","content":{"application/json":{"schema":{"$ref":"#/components/schemas/HTTPValidationError"}}}}},"security":[{"OAuth2PasswordBearer":[]}]}},"/api/docentes/docentes":{"get":{"tags":["docentes"],"summary":"Listar todos los docentes","description":"Este endpoint permite listar todos los docentes registrados en el sistema. Retorna una lista con datos públicos de los docentes.","operationId":"get_docentes_api_docentes_docentes_get","responses":{"200":{"description":"Lista de docentes obtenida exitosamente.","content":{"application/json":{"schema":{"$ref":"#/components/schemas/app__routers__docentes__GeneralResponse"},"example":{"success":true,"data":[{"id":1,"dni":"12345678","apellidos_nombres":"Juan Pérez","id_genero":0,"correo":"juan.perez@example.com","telefono":"987654321","direccion":"Av. Siempre Viva 123","nivel_educacion":"Maestría","profesion":"Ingeniero de Sistemas","cond_laboral":"Tiempo Completo","activo":1,"id_cargo":2},{"id":2,"dni":"87654321","apellidos_nombres":"Ana García","id_genero":1,"correo":"ana.garcia@example.com","direccion":"Calle Falsa 456","nivel_educacion":"Doctorado","profesion":"Investigadora","cond_laboral":"Medio Tiempo","activo":1,"hoja_vida":"https://ejemplo.com/hoja_vida_ana","id_cargo":3,"foto":"https://ejemplo.com/foto_ana.jpg"}],"message":"Datos obtenidos correctamente.","status":200}}}},"401":{"description":"El usuario no está autenticado.","content":{"application/json":{"example":{"detail":"Token inválido o no autorizado."}}}},"503":{"description":"Error del servidor.","content":{"application/json":{"example":{"success":false,"data":[],"message":"Error al obtener los docentes.","status":503}}}}},"security":[{"OAuth2PasswordBearer":[]}]}},"/api/docentes/docente-administrivo/{dni}":{"get":{"tags":["docentes"],"summary":"Obtener un docente por DNI","description":"Este endpoint permite obtener los datos públicos de un docente utilizando su DNI.","operationId":"get_docente_by_dni_api_docentes_docente_administrivo__dni__get","parameters":[{"required":true,"schema":{"title":"Dni","type":"string"},"name":"dni","in":"path"}],"responses":{"200":{"description":"Datos del docente obtenidos exitosamente.","content":{"application/json":{"schema":{"$ref":"#/components/schemas/app__routers__docentes__GeneralResponse"},"example":{"success":true,"data":[{"id":1,"dni":"12345678","apellidos_nombres":"Juan Pérez","id_genero":0,"correo":"juan.perez@example.com","telefono":"987654321","direccion":"Av. Siempre Viva 123","nivel_educacion":"Maestría","profesion":"Ingeniero de Sistemas","cond_laboral":"Tiempo Completo","activo":1,"id_cargo":2}],"message":"Docente obtenido correctamente.","status":200}}}},"404":{"description":"El docente no fue encontrado.","content":{"application/json":{"example":{"detail":"Docente no encontrado."}}}},"401":{"description":"El usuario no está autenticado.","content":{"application/json":{"example":{"detail":"Token inválido o no autorizado."}}}},"422":{"description":"Validation Error","content":{"application/json":{"schema":{"$ref":"#/components/schemas/HTTPValidationError"}}}}},"security":[{"OAuth2PasswordBearer":[]}]}},"/api/egresados/":{"get":{"tags":["egresados"],"summary":"Listar todos los estudiantes activos","description":"Este endpoint permite obtener una lista de todos los estudiantes registrados en el sistema que aún no han egresado.\n    Incluye información relevante como DNI, nombre completo, género, correo, teléfono, dirección, programa de estudios,\n    y otros datos públicos. No incluye información sensible como contraseñas.","operationId":"get_estudiantes_api_egresados__get","responses":{"200":{"description":"Successful Response","content":{"application/json":{"schema":{"$ref":"#/components/schemas/app__routers__egresados__GeneralResponse"}}}}},"security":[{"OAuth2PasswordBearer":[]}]}},"/api/egresados/{dni}":{"get":{"tags":["egresados"],"summary":"Buscar estudiante por DNI","description":"Este endpoint permite buscar y obtener la información pública de un estudiante específico utilizando su DNI.\n    Los datos incluyen información personal, contacto y su programa de estudios, si aplica.","operationId":"get_estudiante_by_dni_api_egresados__dni__get","parameters":[{"required":true,"schema":{"title":"Dni","type":"string"},"name":"dni","in":"path"}],"responses":{"200":{"description":"Successful Response","content":{"application/json":{"schema":{"$ref":"#/components/schemas/app__routers__egresados__GeneralResponse"}}}},"422":{"description":"Validation Error","content":{"application/json":{"schema":{"$ref":"#/components/schemas/HTTPValidationError"}}}}},"security":[{"OAuth2PasswordBearer":[]}]}},"/api/egresados/programa/{id_programa}":{"get":{"tags":["egresados"],"summary":"Buscar estudiantes por programa de estudios","description":"Este endpoint permite obtener la lista de estudiantes que pertenecen a un programa de estudios específico.\n    La búsqueda se realiza utilizando el identificador único del programa de estudios.\n    Incluye información básica y pública de los estudiantes asociados.","operationId":"get_estudiante_by_programa_api_egresados_programa__id_programa__get","parameters":[{"required":true,"schema":{"title":"Id Programa","type":"integer"},"name":"id_programa","in":"path"}],"responses":{"200":{"description":"Successful Response","content":{"application/json":{"schema":{"$ref":"#/components/schemas/app__routers__egresados__GeneralResponse"}}}},"422":{"description":"Validation Error","content":{"application/json":{"schema":{"$ref":"#/components/schemas/HTTPValidationError"}}}}},"security":[{"OAuth2PasswordBearer":[]}]}},"/api/estudiantes/":{"get":{"tags":["estudiante"],"summary":"Listar todos los estudiantes activos","description":"Este endpoint permite obtener una lista de todos los estudiantes registrados en el sistema que aún no han egresado.\n    Incluye información relevante como DNI, nombre completo, género, correo, teléfono, dirección, programa de estudios,\n    y otros datos públicos. No incluye información sensible como contraseñas.","operationId":"get_estudiantes_api_estudiantes__get","responses":{"200":{"description":"Successful Response","content":{"application/json":{"schema":{"$ref":"#/components/schemas/app__routers__estudiantes__GeneralResponse"}}}}},"security":[{"OAuth2PasswordBearer":[]}]}},"/api/estudiantes/{dni}":{"get":{"tags":["estudiante"],"summary":"Buscar estudiante por DNI","description":"Este endpoint permite buscar y obtener la información pública de un estudiante específico utilizando su DNI.\n    Los datos incluyen información personal, contacto y su programa de estudios, si aplica.","operationId":"get_estudiante_by_dni_api_estudiantes__dni__get","parameters":[{"required":true,"schema":{"title":"Dni","type":"string"},"name":"dni","in":"path"}],"responses":{"200":{"description":"Successful Response","content":{"application/json":{"schema":{"$ref":"#/components/schemas/app__routers__estudiantes__GeneralResponse"}}}},"422":{"description":"Validation Error","content":{"application/json":{"schema":{"$ref":"#/components/schemas/HTTPValidationError"}}}}},"security":[{"OAuth2PasswordBearer":[]}]}},"/api/estudiantes/programa/{id_programa}":{"get":{"tags":["estudiante"],"summary":"Buscar estudiantes por programa de estudios","description":"Este endpoint permite obtener la lista de estudiantes que pertenecen a un programa de estudios específico.\n    La búsqueda se realiza utilizando el identificador único del programa de estudios.\n    Incluye información básica y pública de los estudiantes asociados.","operationId":"get_estudiante_by_programa_api_estudiantes_programa__id_programa__get","parameters":[{"required":true,"schema":{"title":"Id Programa","type":"integer"},"name":"id_programa","in":"path"}],"responses":{"200":{"description":"Successful Response","content":{"application/json":{"schema":{"$ref":"#/components/schemas/app__routers__estudiantes__GeneralResponse"}}}},"422":{"description":"Validation Error","content":{"application/json":{"schema":{"$ref":"#/components/schemas/HTTPValidationError"}}}}},"security":[{"OAuth2PasswordBearer":[]}]}},"/api/empresas/":{"get":{"tags":["empresas"],"summary":"Listar todas las Empresas","description":"Lista todas las Empresas disponibles, excluyendo datos sensibles.","operationId":"get_empresas_api_empresas__get","responses":{"200":{"description":"La solicitud se procesó correctamente.","content":{"application/json":{"schema":{"$ref":"#/components/schemas/app__routers__empresas__GeneralResponse"},"example":{"success":true,"data":[{"id":1,"razon_social":"Perez SAC","ruc":"12345678910","correo_institucional":"perezsac@ejemplo.com","ubicacion":"Jr. Ayacucho","contacto":"Juan Perez","cargo":"Jefe RR.HH","celular_telefono":"987654321"}],"message":"Datos obtenidos correctamente.","status":200}}}},"401":{"description":"No autenticado."},"503":{"description":"Error del servidor."}},"security":[{"OAuth2PasswordBearer":[]}]},"post":{"tags":["empresas"],"summary":"Crear una nueva Empresa","description":"Crea una nueva Empresa.","operationId":"create_empresa_endpoint_api_empresas__post","requestBody":{"content":{"application/json":{"schema":{"$ref":"#/components/schemas/EmpresaCreate"}}},"required":true},"responses":{"200":{"description":"Successful Response","content":{"application/json":{"schema":{"$ref":"#/components/schemas/EmpresaResponse"}}}},"201":{"description":"Empresa creada exitosamente."},"401":{"description":"No autenticado."},"503":{"description":"Error del servidor."},"422":{"description":"Validation Error","content":{"application/json":{"schema":{"$ref":"#/components/schemas/HTTPValidationError"}}}}},"security":[{"OAuth2PasswordBearer":[]}]}},"/api/empresas/{empresa_id}":{"put":{"tags":["empresas"],"summary":"Actualizar una Empresa existente","description":"Actualiza una Empresa existente.","operationId":"update_empresa_endpoint_api_empresas__empresa_id__put","parameters":[{"required":true,"schema":{"title":"Empresa Id","type":"integer"},"name":"empresa_id","in":"path"}],"requestBody":{"content":{"application/json":{"schema":{"$ref":"#/components/schemas/EmpresaUpdate"}}},"required":true},"responses":{"200":{"description":"Empresa actualizada exitosamente.","content":{"application/json":{"schema":{"$ref":"#/components/schemas/EmpresaResponse"}}}},"401":{"description":"No autenticado."},"404":{"description":"Empresa no encontrada."},"503":{"description":"Error del servidor."},"422":{"description":"Validation Error","content":{"application/json":{"schema":{"$ref":"#/components/schemas/HTTPValidationError"}}}}},"security":[{"OAuth2PasswordBearer":[]}]},"delete":{"tags":["empresas"],"summary":"Eliminar una Empresa existente","description":"Elimina una Empresa existente.","operationId":"delete_empresa_endpoint_api_empresas__empresa_id__delete","parameters":[{"required":true,"schema":{"title":"Empresa Id","type":"integer"},"name":"empresa_id","in":"path"}],"responses":{"200":{"description":"Empresa eliminada exitosamente.","content":{"application/json":{"schema":{"$ref":"#/components/schemas/EmpresaResponse"}}}},"401":{"description":"No autenticado."},"404":{"description":"Empresa no encontrada."},"503":{"description":"Error del servidor."},"422":{"description":"Validation Error","content":{"application/json":{"schema":{"$ref":"#/components/schemas/HTTPValidationError"}}}}},"security":[{"OAuth2PasswordBearer":[]}]}},"/api/programas/":{"get":{"tags":["programas"],"summary":"Listar todos los ProgramasEstudios","description":"Lista todos los ProgramasEstudios disponibles.","operationId":"get_programas_api_programas__get","responses":{"200":{"description":"La solicitud se procesó correctamente.","content":{"application/json":{"schema":{"$ref":"#/components/schemas/app__routers__programas__GeneralResponse"},"example":{"success":true,"data":[{"id":1,"codigo":"COD123","tipo":"Tipo1","plan_estudio":"Plan1","nombre":"Programa 1","resolucion":"Resolución 1","perfil_egresado":"Perfil 1"}],"message":"Datos obtenidos correctamente.","status":200}}}},"401":{"description":"No autenticado."},"503":{"description":"Error del servidor."}}},"post":{"tags":["programas"],"summary":"Crear un nuevo ProgramaEstudios","description":"Crea un nuevo ProgramaEstudios.","operationId":"create_programa_endpoint_api_programas__post","requestBody":{"content":{"application/json":{"schema":{"$ref":"#/components/schemas/ProgramaCreate"}}},"required":true},"responses":{"200":{"description":"Successful Response","content":{"application/json":{"schema":{"$ref":"#/components/schemas/app__routers__programas__ProgramaResponse"}}}},"201":{"description":"ProgramaEstudios creado exitosamente."},"401":{"description":"No autenticado."},"503":{"description":"Error del servidor."},"422":{"description":"Validation Error","content":{"application/json":{"schema":{"$ref":"#/components/schemas/HTTPValidationError"}}}}}}},"/api/programas/{programa_id}":{"put":{"tags":["programas"],"summary":"Actualizar un ProgramaEstudios existente","description":"Actualiza un ProgramaEstudios existente.","operationId":"update_programa_endpoint_api_programas__programa_id__put","parameters":[{"required":true,"schema":{"title":"Programa Id","type":"integer"},"name":"programa_id","in":"path"}],"requestBody":{"content":{"application/json":{"schema":{"$ref":"#/components/schemas/ProgramaUpdate"}}},"required":true},"responses":{"200":{"description":"ProgramaEstudios actualizado exitosamente.","content":{"application/json":{"schema":{"$ref":"#/components/schemas/app__routers__programas__ProgramaResponse"}}}},"401":{"description":"No autenticado."},"404":{"description":"ProgramaEstudios no encontrado."},"503":{"description":"Error del servidor."},"422":{"description":"Validation Error","content":{"application/json":{"schema":{"$ref":"#/components/schemas/HTTPValidationError"}}}}}},"delete":{"tags":["programas"],"summary":"Eliminar un ProgramaEstudios existente","description":"Elimina un ProgramaEstudios existente.","operationId":"delete_programa_endpoint_api_programas__programa_id__delete","parameters":[{"required":true,"schema":{"title":"Programa Id","type":"integer"},"name":"programa_id","in":"path"}],"responses":{"200":{"description":"ProgramaEstudios eliminado exitosamente.","content":{"application/json":{"schema":{"$ref":"#/components/schemas/app__routers__programas__ProgramaResponse"}}}},"401":{"description":"No autenticado."},"404":{"description":"ProgramaEstudios no encontrado."},"503":{"description":"Error del servidor."},"422":{"description":"Validation Error","content":{"application/json":{"schema":{"$ref":"#/components/schemas/HTTPValidationError"}}}}},"security":[{"OAuth2PasswordBearer":[]}]}},"/api/concepto-ingresos/":{"get":{"tags":["concepto-ingresos"],"summary":"Listar todos los ConceptosIngreso","description":"Lista todos los ConceptosIngreso disponibles.","operationId":"get_conceptos_ingreso_api_concepto_ingresos__get","responses":{"200":{"description":"La solicitud se procesó correctamente.","content":{"application/json":{"schema":{"$ref":"#/components/schemas/app__routers__concepto_ingresos__GeneralResponse"},"example":{"success":true,"data":[{"id":1,"concepto":"Concepto 1","monto":"100.00","codigo":"C001","unidad":"Unidad 1"}],"message":"Datos obtenidos correctamente.","status":200}}}},"401":{"description":"No autenticado."},"503":{"description":"Error del servidor."}},"security":[{"OAuth2PasswordBearer":[]}]},"post":{"tags":["concepto-ingresos"],"summary":"Crear un nuevo ConceptoIngreso","description":"Crea un nuevo ConceptoIngreso.","operationId":"create_concepto_ingreso_endpoint_api_concepto_ingresos__post","requestBody":{"content":{"application/json":{"schema":{"$ref":"#/components/schemas/ConceptoIngresoCreate"}}},"required":true},"responses":{"200":{"description":"Successful Response","content":{"application/json":{"schema":{"$ref":"#/components/schemas/app__routers__concepto_ingresos__ConceptoIngresoResponse"}}}},"201":{"description":"ConceptoIngreso creado exitosamente."},"401":{"description":"No autenticado."},"503":{"description":"Error del servidor."},"422":{"description":"Validation Error","content":{"application/json":{"schema":{"$ref":"#/components/schemas/HTTPValidationError"}}}}},"security":[{"OAuth2PasswordBearer":[]}]}},"/api/concepto-ingresos/{concepto_ingreso_id}":{"put":{"tags":["concepto-ingresos"],"summary":"Actualizar un ConceptoIngreso existente","description":"Actualiza un ConceptoIngreso existente.","operationId":"update_concepto_ingreso_endpoint_api_concepto_ingresos__concepto_ingreso_id__put","parameters":[{"required":true,"schema":{"title":"Concepto Ingreso Id","type":"integer"},"name":"concepto_ingreso_id","in":"path"}],"requestBody":{"content":{"application/json":{"schema":{"$ref":"#/components/schemas/ConceptoIngresoUpdate"}}},"required":true},"responses":{"200":{"description":"ConceptoIngreso actualizado exitosamente.","content":{"application/json":{"schema":{"$ref":"#/components/schemas/app__routers__concepto_ingresos__ConceptoIngresoResponse"}}}},"401":{"description":"No autenticado."},"404":{"description":"ConceptoIngreso no encontrado."},"503":{"description":"Error del servidor."},"422":{"description":"Validation Error","content":{"application/json":{"schema":{"$ref":"#/components/schemas/HTTPValidationError"}}}}},"security":[{"OAuth2PasswordBearer":[]}]},"delete":{"tags":["concepto-ingresos"],"summary":"Eliminar un ConceptoIngreso existente","description":"Elimina un ConceptoIngreso existente.","operationId":"delete_concepto_ingreso_endpoint_api_concepto_ingresos__concepto_ingreso_id__delete","parameters":[{"required":true,"schema":{"title":"Concepto Ingreso Id","type":"integer"},"name":"concepto_ingreso_id","in":"path"}],"responses":{"200":{"description":"ConceptoIngreso eliminado exitosamente.","content":{"application/json":{"schema":{"$ref":"#/components/schemas/app__routers__concepto_ingresos__ConceptoIngresoResponse"}}}},"401":{"description":"No autenticado."},"404":{"description":"ConceptoIngreso no encontrado."},"503":{"description":"Error del servidor."},"422":{"description":"Validation Error","content":{"application/json":{"schema":{"$ref":"#/components/schemas/HTTPValidationError"}}}}},"security":[{"OAuth2PasswordBearer":[]}]}},"/api/ingresos/":{"get":{"tags":["ingresos"],"summary":"Listar todos los Ingresos con sus detalles y conceptos de ingreso","operationId":"get_ingresos_api_ingresos__get","responses":{"200":{"description":"La solicitud se procesó correctamente.","content":{"application/json":{"schema":{"title":"Response Get Ingresos Api Ingresos  Get","type":"array","items":{"$ref":"#/components/schemas/IngresosResponse"}},"example":[{"id":1,"dni":"12345678","usuario":"usuario1","tipo_comprobante":"Boleta","codigo":"ING001","fecha_pago":"2023-01-01T00:00:00","monto_total":"1000.00","estado":"Pagado","ruta_archivo":"/ruta/archivo.pdf","responsable":"Responsable 1","metodo_pago":"Tarjeta","detalles_ingresos":[{"id":1,"id_ingreso":1,"id_concepto":1,"cantidad":2,"subtotal":"200.00","concepto_ingreso":{"id":1,"concepto":"Concepto 1","monto":"100.00","codigo":"C001","unidad":"Unidad 1"}}]}]}}},"401":{"description":"No autenticado."},"503":{"description":"Error del servidor."}},"security":[{"OAuth2PasswordBearer":[]}]},"post":{"tags":["ingresos"],"summary":"Crear un nuevo Ingreso con sus detalles","operationId":"create_ingreso_endpoint_api_ingresos__post","requestBody":{"content":{"application/json":{"schema":{"$ref":"#/components/schemas/IngresosCreate"}}},"required":true},"responses":{"200":{"description":"Successful Response","content":{"application/json":{"schema":{"$ref":"#/components/schemas/IngresosResponse"}}}},"201":{"description":"Ingreso creado exitosamente."},"401":{"description":"No autenticado."},"503":{"description":"Error del servidor."},"422":{"description":"Validation Error","content":{"application/json":{"schema":{"$ref":"#/components/schemas/HTTPValidationError"}}}}},"security":[{"OAuth2PasswordBearer":[]}]}},"/api/ingresos/{codigo}":{"get":{"tags":["ingresos"],"summary":"Buscar un Ingreso por su código","operationId":"get_ingreso_by_codigo_api_ingresos__codigo__get","parameters":[{"required":true,"schema":{"title":"Codigo","type":"string"},"name":"codigo","in":"path"}],"responses":{"200":{"description":"La solicitud se procesó correctamente.","content":{"application/json":{"schema":{"$ref":"#/components/schemas/IngresosResponse"}}}},"401":{"description":"No autenticado."},"404":{"description":"Ingreso no encontrado."},"503":{"description":"Error del servidor."},"422":{"description":"Validation Error","content":{"application/json":{"schema":{"$ref":"#/components/schemas/HTTPValidationError"}}}}},"security":[{"OAuth2PasswordBearer":[]}]}},"/api/egresos/":{"get":{"tags":["egresos"],"summary":"Listar todos los Egresos","operationId":"get_egresos_api_egresos__get","responses":{"200":{"description":"La solicitud se procesó correctamente.","content":{"application/json":{"schema":{"title":"Response Get Egresos Api Egresos  Get","type":"array","items":{"$ref":"#/components/schemas/EgresosResponse"}},"example":[{"id":1,"empresa":"Empresa 1","ruc":"12345678910","concepto":"Concepto 1","tipo_comprobante":"Factura","comprobante":"F001-0001","fecha_pago":"2023-01-01","fecha_registro":"2023-01-01T00:00:00","monto_total":"1000.00","estado":"Pagado","responsable":"Responsable 1"}]}}},"401":{"description":"No autenticado."},"503":{"description":"Error del servidor."}},"security":[{"OAuth2PasswordBearer":[]}]},"post":{"tags":["egresos"],"summary":"Crear un nuevo Egreso","operationId":"create_egreso_endpoint_api_egresos__post","requestBody":{"content":{"application/json":{"schema":{"$ref":"#/components/schemas/EgresosCreate"}}},"required":true},"responses":{"200":{"description":"Successful Response","content":{"application/json":{"schema":{"$ref":"#/components/schemas/EgresosResponse"}}}},"201":{"description":"Egreso creado exitosamente."},"401":{"description":"No autenticado."},"503":{"description":"Error del servidor."},"422":{"description":"Validation Error","content":{"application/json":{"schema":{"$ref":"#/components/schemas/HTTPValidationError"}}}}},"security":[{"OAuth2PasswordBearer":[]}]}},"/api/egresos/{egreso_id}":{"delete":{"tags":["egresos"],"summary":"Eliminar un Egreso existente","operationId":"delete_egreso_endpoint_api_egresos__egreso_id__delete","parameters":[{"required":true,"schema":{"title":"Egreso Id","type":"integer"},"name":"egreso_id","in":"path"}],"responses":{"200":{"description":"Egreso eliminado exitosamente.","content":{"application/json":{"schema":{"$ref":"#/components/schemas/EgresosResponse"}}}},"401":{"description":"No autenticado."},"404":{"description":"Egreso no encontrado."},"503":{"description":"Error del servidor."},"422":{"description":"Validation Error","content":{"application/json":{"schema":{"$ref":"#/components/schemas/HTTPValidationError"}}}}},"security":[{"OAuth2PasswordBearer":[]}]}},"/api/convocatorias/":{"get":{"tags":["convocatorias"],"summary":"Listar todas las Ofertas Laborales Propias Activas o por Empezar","operationId":"get_ofertas_laborales_propias_api_convocatorias__get","responses":{"200":{"description":"La solicitud se procesó correctamente.","content":{"application/json":{"schema":{"title":"Response Get Ofertas Laborales Propias Api Convocatorias  Get","type":"array","items":{"$ref":"#/components/schemas/OfertaLaboralPropiaResponse"}}}}},"401":{"description":"No autenticado."},"503":{"description":"Error del servidor."}},"security":[{"OAuth2PasswordBearer":[]}]},"post":{"tags":["convocatorias"],"summary":"Crear una nueva Oferta Laboral Propia","operationId":"create_oferta_laboral_propia_endpoint_api_convocatorias__post","requestBody":{"content":{"application/json":{"schema":{"$ref":"#/components/schemas/OfertaLaboralPropiaCreate"}}},"required":true},"responses":{"200":{"description":"Successful Response","content":{"application/json":{"schema":{"$ref":"#/components/schemas/OfertaLaboralPropiaResponse"}}}},"201":{"description":"Oferta laboral propia creada exitosamente."},"401":{"description":"No autenticado."},"503":{"description":"Error del servidor."},"422":{"description":"Validation Error","content":{"application/json":{"schema":{"$ref":"#/components/schemas/HTTPValidationError"}}}}},"security":[{"OAuth2PasswordBearer":[]}]}},"/api/convocatorias/{oferta_id}":{"get":{"tags":["convocatorias"],"summary":"Obtener una Oferta Laboral Propia por ID","operationId":"get_oferta_laboral_propia_by_id_api_convocatorias__oferta_id__get","parameters":[{"required":true,"schema":{"title":"Oferta Id","type":"integer"},"name":"oferta_id","in":"path"}],"responses":{"200":{"description":"La solicitud se procesó correctamente.","content":{"application/json":{"schema":{"$ref":"#/components/schemas/OfertaLaboralPropiaDetailResponse"}}}},"401":{"description":"No autenticado."},"404":{"description":"Oferta laboral propia no encontrada."},"503":{"description":"Error del servidor."},"422":{"description":"Validation Error","content":{"application/json":{"schema":{"$ref":"#/components/schemas/HTTPValidationError"}}}}},"security":[{"OAuth2PasswordBearer":[]}]},"put":{"tags":["convocatorias"],"summary":"Actualizar una Oferta Laboral Propia existente","operationId":"update_oferta_laboral_propia_endpoint_api_convocatorias__oferta_id__put","parameters":[{"required":true,"schema":{"title":"Oferta Id","type":"integer"},"name":"oferta_id","in":"path"}],"requestBody":{"content":{"application/json":{"schema":{"$ref":"#/components/schemas/OfertaLaboralPropiaUpdate"}}},"required":true},"responses":{"200":{"description":"Oferta laboral propia actualizada exitosamente.","content":{"application/json":{"schema":{"$ref":"#/components/schemas/OfertaLaboralPropiaResponse"}}}},"401":{"description":"No autenticado."},"404":{"description":"Oferta laboral propia no encontrada."},"503":{"description":"Error del servidor."},"422":{"description":"Validation Error","content":{"application/json":{"schema":{"$ref":"#/components/schemas/HTTPValidationError"}}}}},"security":[{"OAuth2PasswordBearer":[]}]}},"/api/convocatorias-empresas/":{"get":{"tags":["convocatorias-empresas"],"summary":"Listar todas las Ofertas Laborales Activas o por Empezar","operationId":"get_ofertas_laborales_api_convocatorias_empresas__get","responses":{"200":{"description":"La solicitud se procesó correctamente.","content":{"application/json":{"schema":{"title":"Response Get Ofertas Laborales Api Convocatorias Empresas  Get","type":"array","items":{"$ref":"#/components/schemas/OfertaLaboralResponse"}}}}},"401":{"description":"No autenticado."},"503":{"description":"Error del servidor."}},"security":[{"OAuth2PasswordBearer":[]}]}},"/api/convocatorias-empresas/{oferta_id}":{"get":{"tags":["convocatorias-empresas"],"summary":"Obtener una Oferta Laboral por ID","operationId":"get_oferta_laboral_by_id_api_convocatorias_empresas__oferta_id__get","parameters":[{"required":true,"schema":{"title":"Oferta Id","type":"integer"},"name":"oferta_id","in":"path"}],"responses":{"200":{"description":"La solicitud se procesó correctamente.","content":{"application/json":{"schema":{"$ref":"#/components/schemas/OfertaLaboralResponse"}}}},"401":{"description":"No autenticado."},"404":{"description":"Oferta laboral no encontrada."},"503":{"description":"Error del servidor."},"422":{"description":"Validation Error","content":{"application/json":{"schema":{"$ref":"#/components/schemas/HTTPValidationError"}}}}},"security":[{"OAuth2PasswordBearer":[]}]}},"/api/convocatorias-empresas/empresa/{empresa_id}":{"get":{"tags":["convocatorias-empresas"],"summary":"Obtener una lista de Ofertas Laborales Activas o por Empezar por ID de Empresa","operationId":"get_ofertas_laborales_by_empresa_id_api_convocatorias_empresas_empresa__empresa_id__get","parameters":[{"required":true,"schema":{"title":"Empresa Id","type":"integer"},"name":"empresa_id","in":"path"}],"responses":{"200":{"description":"La solicitud se procesó correctamente.","content":{"application/json":{"schema":{"title":"Response Get Ofertas Laborales By Empresa Id Api Convocatorias Empresas Empresa  Empresa Id  Get","type":"array","items":{"$ref":"#/components/schemas/OfertaLaboralResponse"}}}}},"401":{"description":"No autenticado."},"404":{"description":"No se encontraron ofertas laborales activas para la empresa especificada."},"503":{"description":"Error del servidor."},"422":{"description":"Validation Error","content":{"application/json":{"schema":{"$ref":"#/components/schemas/HTTPValidationError"}}}}},"security":[{"OAuth2PasswordBearer":[]}]}},"/auth/token-aplication":{"post":{"tags":["auth"],"summary":"Generar token de aplicación","operationId":"login_auth_token_aplication_post","requestBody":{"content":{"application/json":{"schema":{"$ref":"#/components/schemas/LoginRequest"}}},"required":true},"responses":{"200":{"description":"Successful Response","content":{"application/json":{"schema":{"$ref":"#/components/schemas/LoginResponse"}}}},"422":{"description":"Validation Error","content":{"application/json":{"schema":{"$ref":"#/components/schemas/HTTPValidationError"}}}}}}}},"components":{"schemas":{"CargoResponse":{"title":"CargoResponse","required":["id","descripcion"],"type":"object","properties":{"id":{"title":"Id","type":"integer"},"descripcion":{"title":"Descripcion","type":"string"}}},"ConceptoIngresoCreate":{"title":"ConceptoIngresoCreate","required":["concepto","monto","codigo","unidad"],"type":"object","properties":{"concepto":{"title":"Concepto","type":"string"},"monto":{"title":"Monto","type":"string"},"codigo":{"title":"Codigo","type":"string"},"unidad":{"title":"Unidad","type":"string"}},"description":"Modelo para crear un nuevo ConceptoIngreso."},"ConceptoIngresoUpdate":{"title":"ConceptoIngresoUpdate","type":"object","properties":{"concepto":{"title":"Concepto","type":"string"},"monto":{"title":"Monto","type":"string"},"codigo":{"title":"Codigo","type":"string"},"unidad":{"title":"Unidad","type":"string"}},"description":"Modelo para actualizar un ConceptoIngreso existente."},"DetalleIngresosCreate":{"title":"DetalleIngresosCreate","required":["id_concepto","cantidad","subtotal"],"type":"object","properties":{"id_concepto":{"title":"Id Concepto","type":"integer"},"cantidad":{"title":"Cantidad","type":"integer"},"subtotal":{"title":"Subtotal","type":"string"}}},"DetalleIngresosResponse":{"title":"DetalleIngresosResponse","required":["id","id_ingreso","id_concepto","cantidad","subtotal","concepto_ingreso"],"type":"object","properties":{"id":{"title":"Id","type":"integer"},"id_ingreso":{"title":"Id Ingreso","type":"integer"},"id_concepto":{"title":"Id Concepto","type":"integer"},"cantidad":{"title":"Cantidad","type":"integer"},"subtotal":{"title":"Subtotal","type":"string"},"concepto_ingreso":{"$ref":"#/components/schemas/app__routers__ingresos_caja__ConceptoIngresoResponse"}}},"EgresosCreate":{"title":"EgresosCreate","required":["empresa","ruc","concepto","tipo_comprobante","comprobante","fecha_pago","fecha_registro","monto_total","estado","responsable"],"type":"object","properties":{"empresa":{"title":"Empresa","type":"string"},"ruc":{"title":"Ruc","type":"string"},"concepto":{"title":"Concepto","type":"string"},"tipo_comprobante":{"title":"Tipo Comprobante","type":"string"},"comprobante":{"title":"Comprobante","type":"string"},"fecha_pago":{"title":"Fecha Pago","type":"string","format":"date"},"fecha_registro":{"title":"Fecha Registro","type":"string","format":"date-time"},"monto_total":{"title":"Monto Total","type":"string"},"estado":{"title":"Estado","type":"string"},"responsable":{"title":"Responsable","type":"string"}}},"EgresosResponse":{"title":"EgresosResponse","required":["id","empresa","ruc","concepto","tipo_comprobante","comprobante","fecha_pago","fecha_registro","monto_total","estado","responsable"],"type":"object","properties":{"id":{"title":"Id","type":"integer"},"empresa":{"title":"Empresa","type":"string"},"ruc":{"title":"Ruc","type":"string"},"concepto":{"title":"Concepto","type":"string"},"tipo_comprobante":{"title":"Tipo Comprobante","type":"string"},"comprobante":{"title":"Comprobante","type":"string"},"fecha_pago":{"title":"Fecha Pago","type":"string","format":"date"},"fecha_registro":{"title":"Fecha Registro","type":"string","format":"date-time"},"monto_total":{"title":"Monto Total","type":"string"},"estado":{"title":"Estado","type":"string"},"responsable":{"title":"Responsable","type":"string"}}},"EmpresaCreate":{"title":"EmpresaCreate","required":["razon_social","ubicacion"],"type":"object","properties":{"razon_social":{"title":"Razon Social","type":"string"},"ruc":{"title":"Ruc","type":"string"},"correo_institucional":{"title":"Correo Institucional","type":"string"},"ubicacion":{"title":"Ubicacion","type":"string"},"contacto":{"title":"Contacto","type":"string"},"cargo":{"title":"Cargo","type":"string"},"celular_telefono":{"title":"Celular Telefono","type":"string"}},"description":"Modelo para crear una nueva Empresa."},"EmpresaResponse":{"title":"EmpresaResponse","required":["id","razon_social","ubicacion"],"type":"object","properties":{"id":{"title":"Id","type":"integer"},"razon_social":{"title":"Razon Social","type":"string"},"ruc":{"title":"Ruc","type":"string"},"correo_institucional":{"title":"Correo Institucional","type":"string"},"ubicacion":{"title":"Ubicacion","type":"string"},"contacto":{"title":"Contacto","type":"string"},"cargo":{"title":"Cargo","type":"string"},"celular_telefono":{"title":"Celular Telefono","type":"string"}},"description":"Modelo que define los datos públicos de un Empresa."},"EmpresaUpdate":{"title":"EmpresaUpdate","type":"object","properties":{"razon_social":{"title":"Razon Social","type":"string"},"ruc":{"title":"Ruc","type":"string"},"correo_institucional":{"title":"Correo Institucional","type":"string"},"ubicacion":{"title":"Ubicacion","type":"string"},"contacto":{"title":"Contacto","type":"string"},"cargo":{"title":"Cargo","type":"string"},"celular_telefono":{"title":"Celular Telefono","type":"string"}},"description":"Modelo para actualizar una Empresa existente."},"HTTPValidationError":{"title":"HTTPValidationError","type":"object","properties":{"detail":{"title":"Detail","type":"array","items":{"$ref":"#/components/schemas/ValidationError"}}}},"IngresosCreate":{"title":"IngresosCreate","required":["dni","usuario","tipo_comprobante","codigo","fecha_pago","monto_total","estado","ruta_archivo","responsable","metodo_pago","detalles_ingresos"],"type":"object","properties":{"dni":{"title":"Dni","type":"string"},"usuario":{"title":"Usuario","type":"string"},"tipo_comprobante":{"title":"Tipo Comprobante","type":"string"},"codigo":{"title":"Codigo","type":"string"},"fecha_pago":{"title":"Fecha Pago","type":"string","format":"date-time"},"monto_total":{"title":"Monto Total","type":"string"},"estado":{"title":"Estado","type":"string"},"ruta_archivo":{"title":"Ruta Archivo","type":"string"},"responsable":{"title":"Responsable","type":"string"},"metodo_pago":{"title":"Metodo Pago","type":"string"},"detalles_ingresos":{"title":"Detalles Ingresos","type":"array","items":{"$ref":"#/components/schemas/DetalleIngresosCreate"}}}},"IngresosResponse":{"title":"IngresosResponse","required":["id","dni","usuario","tipo_comprobante","codigo","fecha_pago","monto_total","estado","ruta_archivo","responsable","metodo_pago","detalles_ingresos"],"type":"object","properties":{"id":{"title":"Id","type":"integer"},"dni":{"title":"Dni","type":"string"},"usuario":{"title":"Usuario","type":"string"},"tipo_comprobante":{"title":"Tipo Comprobante","type":"string"},"codigo":{"title":"Codigo","type":"string"},"fecha_pago":{"title":"Fecha Pago","type":"string","format":"date-time"},"monto_total":{"title":"Monto Total","type":"string"},"estado":{"title":"Estado","type":"string"},"ruta_archivo":{"title":"Ruta Archivo","type":"string"},"responsable":{"title":"Responsable","type":"string"},"metodo_pago":{"title":"Metodo Pago","type":"string"},"detalles_ingresos":{"title":"Detalles Ingresos","type":"array","items":{"$ref":"#/components/schemas/DetalleIngresosResponse"}}}},"LoginRequest":{"title":"LoginRequest","required":["dni","password"],"type":"object","properties":{"dni":{"title":"Dni","type":"string"},"password":{"title":"Password","type":"string"}}},"LoginResponse":{"title":"LoginResponse","required":["access_token","token_type","expires_in"],"type":"object","properties":{"access_token":{"title":"Access Token","type":"string"},"token_type":{"title":"Token Type","type":"string"},"expires_in":{"title":"Expires In","type":"string"}}},"OfertaLaboralPropiaCreate":{"title":"OfertaLaboralPropiaCreate","required":["empresa","celular_contacto","titulo","ubicacion","funciones","requisitos","condiciones","beneficios","salario","vacantes","modalidad","turno","fecha_inicio","fecha_fin","link_postulacion","estado","fecha_estado"],"type":"object","properties":{"empresa":{"title":"Empresa","type":"string"},"celular_contacto":{"title":"Celular Contacto","type":"string"},"titulo":{"title":"Titulo","type":"string"},"ubicacion":{"title":"Ubicacion","type":"string"},"funciones":{"title":"Funciones","type":"string"},"requisitos":{"title":"Requisitos","type":"string"},"condiciones":{"title":"Condiciones","type":"string"},"beneficios":{"title":"Beneficios","type":"string"},"salario":{"title":"Salario","type":"string"},"vacantes":{"title":"Vacantes","type":"integer"},"modalidad":{"title":"Modalidad","type":"string"},"turno":{"title":"Turno","type":"string"},"fecha_inicio":{"title":"Fecha Inicio","type":"string","format":"date"},"fecha_fin":{"title":"Fecha Fin","type":"string","format":"date"},"link_postulacion":{"title":"Link Postulacion","type":"string"},"estado":{"title":"Estado","type":"string"},"fecha_estado":{"title":"Fecha Estado","type":"string","format":"date-time"}}},"OfertaLaboralPropiaDetailResponse":{"title":"OfertaLaboralPropiaDetailResponse","required":["id","empresa","celular_contacto","titulo","ubicacion","funciones","requisitos","condiciones","beneficios","salario","vacantes","modalidad","turno","fecha_inicio","fecha_fin","link_postulacion","estado","fecha_estado","postulantes"],"type":"object","properties":{"id":{"title":"Id","type":"integer"},"empresa":{"title":"Empresa","type":"string"},"celular_contacto":{"title":"Celular Contacto","type":"string"},"titulo":{"title":"Titulo","type":"string"},"ubicacion":{"title":"Ubicacion","type":"string"},"funciones":{"title":"Funciones","type":"string"},"requisitos":{"title":"Requisitos","type":"string"},"condiciones":{"title":"Condiciones","type":"string"},"beneficios":{"title":"Beneficios","type":"string"},"salario":{"title":"Salario","type":"string"},"vacantes":{"title":"Vacantes","type":"integer"},"modalidad":{"title":"Modalidad","type":"string"},"turno":{"title":"Turno","type":"string"},"fecha_inicio":{"title":"Fecha Inicio","type":"string","format":"date"},"fecha_fin":{"title":"Fecha Fin","type":"string","format":"date"},"link_postulacion":{"title":"Link Postulacion","type":"string"},"estado":{"title":"Estado","type":"string"},"fecha_estado":{"title":"Fecha Estado","type":"string","format":"date-time"},"postulantes":{"title":"Postulantes","type":"array","items":{"$ref":"#/components/schemas/PostulanteResponse"}}}},"OfertaLaboralPropiaResponse":{"title":"OfertaLaboralPropiaResponse","required":["id","empresa","celular_contacto","titulo","ubicacion","funciones","requisitos","condiciones","beneficios","salario","vacantes","modalidad","turno","fecha_inicio","fecha_fin","link_postulacion","estado","fecha_estado"],"type":"object","properties":{"id":{"title":"Id","type":"integer"},"empresa":{"title":"Empresa","type":"string"},"celular_contacto":{"title":"Celular Contacto","type":"string"},"titulo":{"title":"Titulo","type":"string"},"ubicacion":{"title":"Ubicacion","type":"string"},"funciones":{"title":"Funciones","type":"string"},"requisitos":{"title":"Requisitos","type":"string"},"condiciones":{"title":"Condiciones","type":"string"},"beneficios":{"title":"Beneficios","type":"string"},"salario":{"title":"Salario","type":"string"},"vacantes":{"title":"Vacantes","type":"integer"},"modalidad":{"title":"Modalidad","type":"string"},"turno":{"title":"Turno","type":"string"},"fecha_inicio":{"title":"Fecha Inicio","type":"string","format":"date"},"fecha_fin":{"title":"Fecha Fin","type":"string","format":"date"},"link_postulacion":{"title":"Link Postulacion","type":"string"},"estado":{"title":"Estado","type":"string"},"fecha_estado":{"title":"Fecha Estado","type":"string","format":"date-time"}}},"OfertaLaboralPropiaUpdate":{"title":"OfertaLaboralPropiaUpdate","type":"object","properties":{"empresa":{"title":"Empresa","type":"string"},"celular_contacto":{"title":"Celular Contacto","type":"string"},"titulo":{"title":"Titulo","type":"string"},"ubicacion":{"title":"Ubicacion","type":"string"},"funciones":{"title":"Funciones","type":"string"},"requisitos":{"title":"Requisitos","type":"string"},"condiciones":{"title":"Condiciones","type":"string"},"beneficios":{"title":"Beneficios","type":"string"},"salario":{"title":"Salario","type":"string"},"vacantes":{"title":"Vacantes","type":"integer"},"modalidad":{"title":"Modalidad","type":"string"},"turno":{"title":"Turno","type":"string"},"fecha_inicio":{"title":"Fecha Inicio","type":"string","format":"date"},"fecha_fin":{"title":"Fecha Fin","type":"string","format":"date"},"link_postulacion":{"title":"Link Postulacion","type":"string"},"estado":{"title":"Estado","type":"string"},"fecha_estado":{"title":"Fecha Estado","type":"string","format":"date-time"}}},"OfertaLaboralResponse":{"title":"OfertaLaboralResponse","required":["id","id_empresa","titulo","ubicacion","funciones","requisitos","condiciones","beneficios","salario","vacantes","modalidad","turno","fecha_inicio","fecha_fin","link_postulacion","url_base","estado","fecha_estado"],"type":"object","properties":{"id":{"title":"Id","type":"integer"},"id_empresa":{"title":"Id Empresa","type":"integer"},"titulo":{"title":"Titulo","type":"string"},"ubicacion":{"title":"Ubicacion","type":"string"},"funciones":{"title":"Funciones","type":"string"},"requisitos":{"title":"Requisitos","type":"string"},"condiciones":{"title":"Condiciones","type":"string"},"beneficios":{"title":"Beneficios","type":"string"},"salario":{"title":"Salario","type":"string"},"vacantes":{"title":"Vacantes","type":"integer"},"modalidad":{"title":"Modalidad","type":"string"},"turno":{"title":"Turno","type":"string"},"fecha_inicio":{"title":"Fecha Inicio","type":"string","format":"date"},"fecha_fin":{"title":"Fecha Fin","type":"string","format":"date"},"link_postulacion":{"title":"Link Postulacion","type":"string"},"url_base":{"title":"Url Base","type":"string"},"estado":{"title":"Estado","type":"string"},"fecha_estado":{"title":"Fecha Estado","type":"string","format":"date-time"}}},"PostulanteResponse":{"title":"PostulanteResponse","required":["apellidos","nombres","dni","correo","celular"],"type":"object","properties":{"apellidos":{"title":"Apellidos","type":"string"},"nombres":{"title":"Nombres","type":"string"},"dni":{"title":"Dni","type":"string"},"correo":{"title":"Correo","type":"string"},"celular":{"title":"Celular","type":"string"}}},"ProgramaCreate":{"title":"ProgramaCreate","required":["codigo","tipo","plan_estudio","nombre","resolucion","perfil_egresado"],"type":"object","properties":{"codigo":{"title":"Codigo","type":"string"},"tipo":{"title":"Tipo","type":"string"},"plan_estudio":{"title":"Plan Estudio","type":"string"},"nombre":{"title":"Nombre","type":"string"},"resolucion":{"title":"Resolucion","type":"string"},"perfil_egresado":{"title":"Perfil Egresado","type":"string"}},"description":"Modelo para crear un nuevo ProgramaEstudios."},"ProgramaUpdate":{"title":"ProgramaUpdate","type":"object","properties":{"codigo":{"title":"Codigo","type":"string"},"tipo":{"title":"Tipo","type":"string"},"plan_estudio":{"title":"Plan Estudio","type":"string"},"nombre":{"title":"Nombre","type":"string"},"resolucion":{"title":"Resolucion","type":"string"},"perfil_egresado":{"title":"Perfil Egresado","type":"string"}},"description":"Modelo para actualizar un ProgramaEstudios existente."},"ValidationError":{"title":"ValidationError","required":["loc","msg","type"],"type":"object","properties":{"loc":{"title":"Location","type":"array","items":{"anyOf":[{"type":"string"},{"type":"integer"}]}},"msg":{"title":"Message","type":"string"},"type":{"title":"Error Type","type":"string"}}},"app__routers__administrativos__DocenteResponse":{"title":"DocenteResponse","required":["id","dni","apellidos_nombres","fecha_nac","direccion","correo","telefono","id_genero","nivel_educacion","profesion","hoja_vida","cond_laboral","id_cargo","cargo_inmutable","carga_academica","id_programa_estudio","password","activo","reset_password","token_password","foto","cargo"],"type":"object","properties":{"id":{"title":"Id","type":"integer"},"dni":{"title":"Dni","type":"string"},"apellidos_nombres":{"title":"Apellidos Nombres","type":"string"},"fecha_nac":{"title":"Fecha Nac","type":"string","format":"date"},"direccion":{"title":"Direccion","type":"string"},"correo":{"title":"Correo","type":"string"},"telefono":{"title":"Telefono","type":"string"},"id_genero":{"title":"Id Genero","type":"integer"},"nivel_educacion":{"title":"Nivel Educacion","type":"string"},"profesion":{"title":"Profesion","type":"string"},"hoja_vida":{"title":"Hoja Vida","type":"string"},"cond_laboral":{"title":"Cond Laboral","type":"string"},"id_cargo":{"title":"Id Cargo","type":"integer"},"cargo_inmutable":{"title":"Cargo Inmutable","type":"integer"},"carga_academica":{"title":"Carga Academica","type":"integer"},"id_programa_estudio":{"title":"Id Programa Estudio","type":"integer"},"password":{"title":"Password","type":"string"},"activo":{"title":"Activo","type":"integer"},"reset_password":{"title":"Reset Password","type":"integer"},"token_password":{"title":"Token Password","type":"string"},"foto":{"title":"Foto","type":"string"},"cargo":{"$ref":"#/components/schemas/CargoResponse"}}},"app__routers__concepto_ingresos__ConceptoIngresoResponse":{"title":"ConceptoIngresoResponse","required":["id","concepto","monto","codigo","unidad"],"type":"object","properties":{"id":{"title":"Id","type":"integer"},"concepto":{"title":"Concepto","type":"string"},"monto":{"title":"Monto","type":"string"},"codigo":{"title":"Codigo","type":"string"},"unidad":{"title":"Unidad","type":"string"}},"description":"Modelo que define los datos públicos de un ConceptoIngreso."},"app__routers__concepto_ingresos__GeneralResponse":{"title":"GeneralResponse","required":["success","data","message","status"],"type":"object","properties":{"success":{"title":"Success","type":"boolean"},"data":{"title":"Data","type":"array","items":{"$ref":"#/components/schemas/app__routers__concepto_ingresos__ConceptoIngresoResponse"}},"message":{"title":"Message","type":"string"},"status":{"title":"Status","type":"integer"}},"description":"Modelo general de respuesta con estructura estándar."},"app__routers__docentes__DocenteResponse":{"title":"DocenteResponse","required":["id","dni","apellidos_nombres","id_genero","correo"],"type":"object","properties":{"id":{"title":"Id","type":"integer"},"dni":{"title":"Dni","type":"string"},"apellidos_nombres":{"title":"Apellidos Nombres","type":"string"},"id_genero":{"title":"Id Genero","type":"integer"},"correo":{"title":"Correo","type":"string"},"telefono":{"title":"Telefono","type":"string"},"direccion":{"title":"Direccion","type":"string"},"nivel_educacion":{"title":"Nivel Educacion","type":"string"},"profesion":{"title":"Profesion","type":"string"},"cond_laboral":{"title":"Cond Laboral","type":"string"},"activo":{"title":"Activo","type":"integer"},"hoja_vida":{"title":"Hoja Vida","type":"string"},"id_cargo":{"title":"Id Cargo","type":"integer"},"foto":{"title":"Foto","type":"string"}},"description":"Modelo que define los datos públicos de un docente."},"app__routers__docentes__GeneralResponse":{"title":"GeneralResponse","required":["success","data","message","status"],"type":"object","properties":{"success":{"title":"Success","type":"boolean"},"data":{"title":"Data","type":"array","items":{"$ref":"#/components/schemas/app__routers__docentes__DocenteResponse"}},"message":{"title":"Message","type":"string"},"status":{"title":"Status","type":"integer"}},"description":"Modelo general de respuesta con estructura estándar."},"app__routers__egresados__EstudianteResponse":{"title":"EstudianteResponse","required":["id","dni","apellidos_nombres","id_genero","id_semestre"],"type":"object","properties":{"id":{"title":"Id","type":"integer"},"dni":{"title":"Dni","type":"string"},"apellidos_nombres":{"title":"Apellidos Nombres","type":"string"},"id_genero":{"title":"Id Genero","type":"integer"},"correo":{"title":"Correo","type":"string"},"telefono":{"title":"Telefono","type":"string"},"direccion":{"title":"Direccion","type":"string"},"anio_ingreso":{"title":"Anio Ingreso","type":"string"},"id_semestre":{"title":"Id Semestre","type":"integer"},"seccion":{"title":"Seccion","type":"string"},"turno":{"title":"Turno","type":"string"},"discapacidad":{"title":"Discapacidad","type":"string"},"programa":{"$ref":"#/components/schemas/app__routers__egresados__ProgramaResponse"}},"description":"Modelo que define los datos públicos de un estudiante."},"app__routers__egresados__GeneralResponse":{"title":"GeneralResponse","required":["success","data","message","status"],"type":"object","properties":{"success":{"title":"Success","type":"boolean"},"data":{"title":"Data","type":"array","items":{"$ref":"#/components/schemas/app__routers__egresados__EstudianteResponse"}},"message":{"title":"Message","type":"string"},"status":{"title":"Status","type":"integer"}},"description":"Modelo general de respuesta con estructura estándar."},"app__routers__egresados__ProgramaResponse":{"title":"ProgramaResponse","required":["id","nombre"],"type":"object","properties":{"id":{"title":"Id","type":"integer"},"nombre":{"title":"Nombre","type":"string"}},"description":"Modelo que define los datos públicos de un programa."},"app__routers__empresas__GeneralResponse":{"title":"GeneralResponse","required":["success","data","message","status"],"type":"object","properties":{"success":{"title":"Success","type":"boolean"},"data":{"title":"Data","type":"array","items":{"$ref":"#/components/schemas/EmpresaResponse"}},"message":{"title":"Message","type":"string"},"status":{"title":"Status","type":"integer"}},"description":"Modelo general de respuesta con estructura estándar."},"app__routers__estudiantes__EstudianteResponse":{"title":"EstudianteResponse","required":["id","dni","apellidos_nombres","id_genero","id_semestre"],"type":"object","properties":{"id":{"title":"Id","type":"integer"},"dni":{"title":"Dni","type":"string"},"apellidos_nombres":{"title":"Apellidos Nombres","type":"string"},"id_genero":{"title":"Id Genero","type":"integer"},"correo":{"title":"Correo","type":"string"},"telefono":{"title":"Telefono","type":"string"},"direccion":{"title":"Direccion","type":"string"},"anio_ingreso":{"title":"Anio Ingreso","type":"string"},"id_semestre":{"title":"Id Semestre","type":"integer"},"seccion":{"title":"Seccion","type":"string"},"turno":{"title":"Turno","type":"string"},"discapacidad":{"title":"Discapacidad","type":"string"},"programa":{"$ref":"#/components/schemas/app__routers__estudiantes__ProgramaResponse"}},"description":"Modelo que define los datos públicos de un estudiante."},"app__routers__estudiantes__GeneralResponse":{"title":"GeneralResponse","required":["success","data","message","status"],"type":"object","properties":{"success":{"title":"Success","type":"boolean"},"data":{"title":"Data","type":"array","items":{"$ref":"#/components/schemas/app__routers__estudiantes__EstudianteResponse"}},"message":{"title":"Message","type":"string"},"status":{"title":"Status","type":"integer"}},"description":"Modelo general de respuesta con estructura estándar."},"app__routers__estudiantes__ProgramaResponse":{"title":"ProgramaResponse","required":["id","nombre"],"type":"object","properties":{"id":{"title":"Id","type":"integer"},"nombre":{"title":"Nombre","type":"string"}},"description":"Modelo que define los datos públicos de un programa."},"app__routers__ingresos_caja__ConceptoIngresoResponse":{"title":"ConceptoIngresoResponse","required":["id","concepto","monto","codigo","unidad"],"type":"object","properties":{"id":{"title":"Id","type":"integer"},"concepto":{"title":"Concepto","type":"string"},"monto":{"title":"Monto","type":"string"},"codigo":{"title":"Codigo","type":"string"},"unidad":{"title":"Unidad","type":"string"}}},"app__routers__programas__GeneralResponse":{"title":"GeneralResponse","required":["success","data","message","status"],"type":"object","properties":{"success":{"title":"Success","type":"boolean"},"data":{"title":"Data","type":"array","items":{"$ref":"#/components/schemas/app__routers__programas__ProgramaResponse"}},"message":{"title":"Message","type":"string"},"status":{"title":"Status","type":"integer"}},"description":"Modelo general de respuesta con estructura estándar."},"app__routers__programas__ProgramaResponse":{"title":"ProgramaResponse","required":["id","codigo","tipo","plan_estudio","nombre","resolucion","perfil_egresado"],"type":"object","properties":{"id":{"title":"Id","type":"integer"},"codigo":{"title":"Codigo","type":"string"},"tipo":{"title":"Tipo","type":"string"},"plan_estudio":{"title":"Plan Estudio","type":"string"},"nombre":{"title":"Nombre","type":"string"},"resolucion":{"title":"Resolucion","type":"string"},"perfil_egresado":{"title":"Perfil Egresado","type":"string"}},"description":"Modelo que define los datos públicos de un ProgramaEstudios."}},"securitySchemes":{"OAuth2PasswordBearer":{"type":"oauth2","flows":{"password":{"scopes":{},"tokenUrl":"/auth/login"}}}}}}